timebox/__init__.py
timebox/__main__.py
timebox/common.py
timebox/config.py
timebox/engine.py
timebox/format_report.py
timebox/pipe.py
timebox/rclone.py
timebox/utils.py
timebox/input_providers/__init__.py
timebox/input_providers/base.py
timebox/input_providers/command.py
timebox/input_providers/folder.py
timebox/input_providers/postgres.py
timebox/notification_providers/__init__.py
timebox/notification_providers/base.py
timebox/notification_providers/command.py
timebox/notification_providers/smtp.py
timebox/notification_providers/webhook.py
timebox/output_providers/__init__.py
timebox/output_providers/base.py
timebox/output_providers/folder.py
timebox/output_providers/rclone.py
timebox/rotation_providers/__init__.py
timebox/rotation_providers/base.py
timebox/rotation_providers/decaying_rotation.py
timebox/rotation_providers/period_rotation.py
timebox/rotation_providers/simple_rotation.py
backup_timebox-0.2.1.dist-info/METADATA
backup_timebox-0.2.1.dist-info/WHEEL
backup_timebox-0.2.1.dist-info/entry_points.txt
backup_timebox-0.2.1.dist-info/top_level.txt
backup_timebox-0.2.1.dist-info/RECORD
